Metadata-Version: 1.0
Name: distributions-Statistics
Version: 0.1
Summary: Gaussian distributions
Home-page: UNKNOWN
Author: Kaan Mavice
Author-email: kaan.mavice@gmail.com
License: UNKNOWN
Platform: UNKNOWN
